{
  "swiper": [
    {
      "id": 1,
      "imgUrl": "http://img1.qunarzz.com/piao/fusion/1812/e0/7aed5dde53dabe02.jpg_750x200_9b7a65fd.jpg"
    },
    {
      "id": 2,
      "imgUrl": "http://img1.qunarzz.com/piao/fusion/1811/7c/8e5c4ab8ee8b7402.jpg_750x200_dd7a38dd.jpg"
    },
    {
      "id": 3,
      "imgUrl": "http://img1.qunarzz.com/piao/fusion/1811/b7/1e9c4ca462741f02.jpg_750x200_842d5261.jpg"
    },
    {
      "id": 4,
      "imgUrl": "http://img1.qunarzz.com/piao/fusion/1812/d5/4d86b63fd4c8202.jpg_750x200_146446f4.jpg"
    },
    {
      "id": 5,
      "imgUrl": "http://img1.qunarzz.com/piao/fusion/1809/61/44400d6591891202.jpg_750x200_7565a05c.jpg"
    }
  ],
	"list": [
			{
				"id": 1,
				"type": "公告速递",
				"title": "开心一笑",
				"img": "/static/list/1.png",
				"content": "笑哭,夫妻间也满满的都是套路。小时候胆小怕黑怕鬼,每次上厕所都要父母陪同",
				"date": "2018/12/24 上午 10:08:18"
			},
			{
				"id": 2,
				"type": "公告速递",
				"title": "开心一笑",
				"img": "/static/list/2.jpg",
				"content": "笑哭,夫妻间也满满的都是套路。小时候胆小怕黑怕鬼,每次上厕所都要父母陪同",
				"date": "2018/11/24 上午 10:08:18"
			},
			{
				"id": 3,
				"type": "公告速递",
				"title": "开心一笑",
				"img": "/static/list/3.jpg",
				"content": "笑哭,夫妻间也满满的都是套路。小时候胆小怕黑怕鬼,每次上厕所都要父母陪同",
				"date": "2018/10/24 上午 10:08:18"
			},{
				"id": 4,
				"type": "培训动态",
				"title": "开心一笑",
				"img": "/static/list/4.jpg",
				"content": "笑哭,夫妻间也满满的都是套路。小时候胆小怕黑怕鬼,每次上厕所都要父母陪同",
				"date": "2018/09/24 上午 10:08:18"
			},{
				"id": 5,
				"type": "培训动态",
				"title": "开心一笑",
				"img": "/static/list/5.jpg",
				"content": "笑哭,夫妻间也满满的都是套路。小时候胆小怕黑怕鬼,每次上厕所都要父母陪同",
				"date": "2018/08/24 上午 10:08:18"
			}
	]
}